codebuddy_agent_sdk/__init__.py
codebuddy_agent_sdk/_binary.py
codebuddy_agent_sdk/_errors.py
codebuddy_agent_sdk/_message_parser.py
codebuddy_agent_sdk/_version.py
codebuddy_agent_sdk/client.py
codebuddy_agent_sdk/py.typed
codebuddy_agent_sdk/query.py
codebuddy_agent_sdk/types.py
codebuddy_agent_sdk/bin/codebuddy
codebuddy_agent_sdk/mcp/__init__.py
codebuddy_agent_sdk/mcp/create_sdk_mcp_server.py
codebuddy_agent_sdk/mcp/sdk_control_server_transport.py
codebuddy_agent_sdk/mcp/types.py
codebuddy_agent_sdk/transport/__init__.py
codebuddy_agent_sdk/transport/base.py
codebuddy_agent_sdk/transport/subprocess.py
codebuddy_agent_sdk-0.3.32.dist-info/METADATA
codebuddy_agent_sdk-0.3.32.dist-info/WHEEL
codebuddy_agent_sdk-0.3.32.dist-info/RECORD
