Metadata-Version: 2.4
Name: codebuddy-agent-sdk
Version: 0.3.32
Summary: CodeBuddy Code SDK for Python
Author-email: ninoyi <ninoyi@tencent.com>
Keywords: agent,ai,codebuddy,sdk
Classifier: Development Status :: 3 - Alpha
Classifier: Intended Audience :: Developers
Classifier: Programming Language :: Python :: 3
Classifier: Programming Language :: Python :: 3.10
Classifier: Programming Language :: Python :: 3.11
Classifier: Programming Language :: Python :: 3.12
Classifier: Programming Language :: Python :: 3.13
Classifier: Typing :: Typed
Requires-Python: >=3.10
Requires-Dist: typing-extensions>=4.0.0
Provides-Extra: dev
Requires-Dist: mypy>=1.10.0; extra == 'dev'
Requires-Dist: pytest-asyncio>=0.23.0; extra == 'dev'
Requires-Dist: pytest>=8.0.0; extra == 'dev'
Requires-Dist: ruff>=0.4.0; extra == 'dev'
